fastapi_project_pattern/__init__.py
fastapi_project_pattern/create_project.py
fastapi_project_pattern/requirements-dev.txt
fastapi_project_pattern-1.1.8.dist-info/LICENSE
fastapi_project_pattern-1.1.8.dist-info/WHEEL
fastapi_project_pattern-1.1.8.dist-info/METADATA
fastapi_project_pattern-1.1.8.dist-info/RECORD
