Metadata-Version: 2.1
Name: fastapi_project_pattern
Version: 1.1.8
Summary: This project was created as a shortcut for fastapi project creation
Author-email: Le Tanh Sang <sang.tanhle@gmail.com>
Classifier: License :: OSI Approved :: GNU General Public License v3 or later (GPLv3+)
Requires-Dist: GitPython >= 3.1.24
Project-URL: Source, https://github.com/kampvie/fastapi_project_pattern
